manim_rubikscube/__init__.py
manim_rubikscube/__main__.py
manim_rubikscube/cube.py
manim_rubikscube/cube_animations.py
manim_rubikscube/cube_utils.py
manim_rubikscube/cubie.py
manim_rubikscube-0.1.0.dist-info/entry_points.txt
manim_rubikscube-0.1.0.dist-info/LICENSE
manim_rubikscube-0.1.0.dist-info/WHEEL
manim_rubikscube-0.1.0.dist-info/METADATA
manim_rubikscube-0.1.0.dist-info/RECORD
