Metadata-Version: 2.1
Name: manim-rubikscube
Version: 0.1.0
Summary: A Manim implementation of the classic Rubik's Cube
Home-page: https://github.com/WampyCakes/manim-rubikscube
License: MIT
Author: KingWampy
Author-email: fake-noreply@email.com
Classifier: License :: OSI Approved :: MIT License
Classifier: Programming Language :: Python :: 2
Classifier: Programming Language :: Python :: 2.7
Classifier: Programming Language :: Python :: 3
Classifier: Programming Language :: Python :: 3.4
Classifier: Programming Language :: Python :: 3.5
Classifier: Programming Language :: Python :: 3.6
Classifier: Programming Language :: Python :: 3.7
Classifier: Programming Language :: Python :: 3.8
Classifier: Programming Language :: Python :: 3.9
Requires-Dist: importlib-metadata; python_version < "3.8"
Requires-Dist: kociemba-manim-rubikscube
Requires-Dist: manim
Project-URL: Repository, https://github.com/WampyCakes/manim-rubikscube
